[
    {
        "hora": "16:30",
        "competición": "Serie A",
        "equipos": "Torino vs Udinese",
        "canales": [
            {
                "nombre": "Disney+",
                "calidad": "Calidad 720p",
                "enlace": "https://librefutbol.su/eventos/?r=aHR0cHM6Ly9lbnZpdm8xLmNvbS9jYW5hbC5waHA/c3RyZWFtPWRpc25leTQ="
            }
        ]
    },
    {
        "hora": "16:30",
        "competición": "Serie A",
        "equipos": "Cagliari vs Fiorentina",
        "canales": [
            {
                "nombre": "Disney+",
                "calidad": "Calidad 720p",
                "enlace": "https://librefutbol.su/eventos/?r=aHR0cHM6Ly9lbnZpdm8xLmNvbS9jYW5hbC5waHA/c3RyZWFtPWRpc25leTE="
            }
        ]
    },
    {
        "hora": "16:30",
        "competición": "Serie A",
        "equipos": "Genoa vs Lazio",
        "canales": [
            {
                "nombre": "Disney+",
                "calidad": "Calidad 720p",
                "enlace": "https://librefutbol.su/eventos/?r=aHR0cHM6Ly9lbnZpdm8xLmNvbS9jYW5hbC5waHA/c3RyZWFtPWRpc25leTI="
            },
            {
                "nombre": "ESPN 3 MX",
                "calidad": "Calidad 720p",
                "enlace": "https://librefutbol.su/eventos/?r=aHR0cHM6Ly9lbnZpdm8xLmNvbS9jYW5hbC5waHA/c3RyZWFtPWVzcG4zbXg="
            },
            {
                "nombre": "Sport TV4",
                "calidad": "Calidad 720p",
                "enlace": "https://librefutbol.su/eventos/?r=aHR0cHM6Ly9lbnZpdm8xLmNvbS9jYW5hbC5waHA/c3RyZWFtPXNwb3J0dl80cHQ="
            }
        ]
    },
    {
        "hora": "16:30",
        "competición": "Serie A",
        "equipos": "Parma vs Juventus",
        "canales": [
            {
                "nombre": "Disney+",
                "calidad": "Calidad 720p",
                "enlace": "https://librefutbol.su/eventos/?r=aHR0cHM6Ly9lbnZpdm8xLmNvbS9jYW5hbC5waHA/c3RyZWFtPWRpc25leTM="
            },
            {
                "nombre": "FOX Deportes",
                "calidad": "Calidad 720p",
                "enlace": "https://librefutbol.su/eventos/?r=aHR0cHM6Ly9lbnZpdm8xLmNvbS9jYW5hbC5waHA/c3RyZWFtPWZveF9kZXBvcnRlc191c2E="
            },
            {
                "nombre": "ESPN 3 BR",
                "calidad": "Calidad 720p",
                "enlace": "https://librefutbol.su/eventos/?r=aHR0cHM6Ly9lbnZpdm8xLmNvbS9jYW5hbC5waHA/c3RyZWFtPWVzcG4zYnI="
            },
            {
                "nombre": "Sport TV2",
                "calidad": "Calidad 720p",
                "enlace": "https://librefutbol.su/eventos/?r=aHR0cHM6Ly9lbnZpdm8xLmNvbS9jYW5hbC5waHA/c3RyZWFtPXNwb3J0dl8ycHQ="
            }
        ]
    },
    {
        "hora": "17:00",
        "competición": "LaLiga",
        "equipos": "Athletic Club vs Las Palmas",
        "canales": [
            {
                "nombre": "ESPN 2",
                "calidad": "Calidad 720p",
                "enlace": "https://librefutbol.su/eventos/?r=aHR0cHM6Ly9lbnZpdm8xLmNvbS9jYW5hbC5waHA/c3RyZWFtPWVzcG4y"
            },
            {
                "nombre": "ESPN Deportes",
                "calidad": "Calidad 720p",
                "enlace": "https://librefutbol.su/eventos/?r=aHR0cHM6Ly9lbnZpdm8xLmNvbS9jYW5hbC5waHA/c3RyZWFtPWVzcG5kZXBvcnRlcw=="
            },
            {
                "nombre": "ESPN+",
                "calidad": "Calidad 720p",
                "enlace": "https://librefutbol.su/eventos/?r=aHR0cHM6Ly9lbnZpdm8xLmNvbS9jYW5hbC5waHA/c3RyZWFtPWVzcG5wbHVzOQ=="
            },
            {
                "nombre": "ESPN 4 BR",
                "calidad": "Calidad 720p",
                "enlace": "https://librefutbol.su/eventos/?r=aHR0cHM6Ly9lbnZpdm8xLmNvbS9jYW5hbC5waHA/c3RyZWFtPWVzcG40YnI="
            },
            {
                "nombre": "DAZN Eleven 1 PT",
                "calidad": "Calidad 720p",
                "enlace": "https://librefutbol.su/eventos/?r=aHR0cHM6Ly9lbnZpdm8xLmNvbS9jYW5hbC5waHA/c3RyZWFtPWVsZXZlbjFfcHQ="
            }
        ]
    },
    {
        "hora": "17:00",
        "competición": "LaLiga",
        "equipos": "Celta de Vigo vs Villarreal",
        "canales": [
            {
                "nombre": "ESPN+",
                "calidad": "Calidad 720p",
                "enlace": "https://librefutbol.su/eventos/?r=aHR0cHM6Ly9lbnZpdm8xLmNvbS9jYW5hbC5waHA/c3RyZWFtPWVzcG5wbHVzNg=="
            },
            {
                "nombre": "DAZN Eleven 3 PT",
                "calidad": "Calidad 720p",
                "enlace": "https://librefutbol.su/eventos/?r=aHR0cHM6Ly9lbnZpdm8xLmNvbS9jYW5hbC5waHA/c3RyZWFtPWVsZXZlbjNfcHQ="
            }
        ]
    },
    {
        "hora": "19:00",
        "competición": "Premier League",
        "equipos": "Arsenal vs Crystal Palace",
        "canales": []
    },
    {
        "hora": "19:00",
        "competición": "Copa Italiana",
        "equipos": "Internazionale vs Milan",
        "canales": []
    },
    {
        "hora": "19:30",
        "competición": "LaLiga",
        "equipos": "Getafe vs Real Madrid",
        "canales": []
    },
    {
        "hora": "19:30",
        "competición": "LaLiga",
        "equipos": "Deportivo Alavés vs Real Sociedad",
        "canales": []
    },
    {
        "hora": "22:00",
        "competición": "Copa Libertadores",
        "equipos": "San Antonio Bulo Bulo vs Vélez Sarsfield",
        "canales": []
    },
    {
        "hora": "22:00",
        "competición": "Copa Libertadores",
        "equipos": "Olimpia vs Peñarol",
        "canales": []
    },
    {
        "hora": "22:00",
        "competición": "Copa Sudamericana",
        "equipos": "Unión Española vs Fluminense",
        "canales": []
    },
    {
        "hora": "22:00",
        "competición": "Copa Sudamericana",
        "equipos": "Huracán vs América de Cali",
        "canales": []
    },
    {
        "hora": "00:30",
        "competición": "Copa Libertadores",
        "equipos": "Libertad vs São Paulo",
        "canales": []
    },
    {
        "hora": "00:30",
        "competición": "Copa Libertadores",
        "equipos": "Independiente del Valle vs River Plate",
        "canales": []
    },
    {
        "hora": "00:30",
        "competición": "Copa Libertadores",
        "equipos": "Estudiantes vs Botafogo",
        "canales": []
    },
    {
        "hora": "00:30",
        "competición": "Copa Sudamericana",
        "equipos": "Caracas vs Atlético Mineiro",
        "canales": []
    },
    {
        "hora": "00:30",
        "competición": "Copa Sudamericana",
        "equipos": "Vitória vs Cerro Largo",
        "canales": []
    },
    {
        "hora": "02:00",
        "competición": "Liga Campeones CONCACAF",
        "equipos": "Tigres UANL vs Cruz Azul",
        "canales": []
    },
    {
        "hora": "02:00",
        "competición": "Copa Sudamericana",
        "equipos": "Atlético Grau vs Sportivo Luqueño",
        "canales": []
    },
    {
        "hora": "02:00",
        "competición": "Copa Sudamericana",
        "equipos": "Mushuc Runa vs Unión Santa Fe",
        "canales": []
    },
    {
        "hora": "02:00",
        "competición": "Copa Libertadores",
        "equipos": "Atlético Bucaramanga vs Fortaleza",
        "canales": []
    }
]