[
    {
        "hora": "16:15",
        "competición": "Liga Profesional Saudi",
        "equipos": "Al Raed vs Al Hilal",
        "canales": [
            {
                "nombre": "TNT Sports",
                "calidad": "Calidad 720p",
                "enlace": "https://librefutbol.su/tnt-sports-en-vivo-online-aey/"
            },
            {
                "nombre": "SSC Extra 1 SA",
                "calidad": "Calidad 1080p",
                "enlace": "https://librefutbol.su/eventos/?r=aHR0cHM6Ly9lbnZpdm8xLmNvbS9jb2JvLmh0bWw/aWQ9U1NDX0VYVFJBMQ=="
            },
            {
                "nombre": "FOX Deportes",
                "calidad": "Calidad 720p",
                "enlace": "https://librefutbol.su/eventos/?r=aHR0cHM6Ly9lbnZpdm8xLmNvbS9jYW5hbC5waHA/c3RyZWFtPWZveF9kZXBvcnRlc191c2E="
            },
            {
                "nombre": "Sport TV3",
                "calidad": "Calidad 720p",
                "enlace": "https://librefutbol.su/eventos/?r=aHR0cHM6Ly9lbnZpdm8xLmNvbS9jYW5hbC5waHA/c3RyZWFtPXNwb3J0dl8zcHQ="
            }
        ]
    },
    {
        "hora": "16:25",
        "competición": "Liga Profesional Saudi",
        "equipos": "Al-Ahli vs Al Taawon",
        "canales": [
            {
                "nombre": "SSC Extra 2 SA",
                "calidad": "Calidad 1080p",
                "enlace": "https://librefutbol.su/eventos/?r=aHR0cHM6Ly9lbnZpdm8xLmNvbS9jb2JvLmh0bWw/aWQ9U1NDX0VYVFJBMg=="
            }
        ]
    },
    {
        "hora": "18:00",
        "competición": "Liga Profesional Saudi",
        "equipos": "Al Nassr vs Al Ittihad",
        "canales": [
            {
                "nombre": "TNT Sports",
                "calidad": "Calidad 720p",
                "enlace": "https://librefutbol.su/tnt-sports-en-vivo-online-aey/"
            },
            {
                "nombre": "SSC Sport 1 SA",
                "calidad": "Calidad 1080p",
                "enlace": "https://librefutbol.su/eventos/?r=aHR0cHM6Ly92aXZvZnl0di5jb20vY29iby5odG1sP2lkPVNTQzE="
            },
            {
                "nombre": "FOX Deportes",
                "calidad": "Calidad 720p",
                "enlace": "https://librefutbol.su/eventos/?r=aHR0cHM6Ly9lbnZpdm8xLmNvbS9jYW5hbC5waHA/c3RyZWFtPWZveF9kZXBvcnRlc191c2E="
            },
            {
                "nombre": "Azteca Deportes",
                "calidad": "Calidad 720p",
                "enlace": "https://librefutbol.su/eventos/?r=aHR0cHM6Ly9lbnZpdm8xLmNvbS9jYW5hbC5waHA/c3RyZWFtPWF6dGVjYV9kZXBvcnRlcw=="
            },
            {
                "nombre": "Sport TV1",
                "calidad": "Calidad 720p",
                "enlace": "https://librefutbol.su/eventos/?r=aHR0cHM6Ly9lbnZpdm8xLmNvbS9jYW5hbC5waHA/c3RyZWFtPXNwb3J0dl8xcHQ="
            }
        ]
    },
    {
        "hora": "19:00",
        "competición": "Liga de Campeones de la UEFA",
        "equipos": "PSG vs Arsenal",
        "canales": [
            {
                "nombre": "ESPN",
                "calidad": "Calidad 720p",
                "enlace": "https://librefutbol.su/espn-1/"
            },
            {
                "nombre": "Fox Sports",
                "calidad": "Calidad 720p",
                "enlace": "https://librefutbol.su/eventos/?r=aHR0cHM6Ly9lbnZpdm8xLmNvbS9jYW5hbC5waHA/c3RyZWFtPWZveHNwb3J0cw=="
            }
        ]
    },
    {
        "hora": "21:00",
        "competición": "Liga Nacional",
        "equipos": "Cobán Imperial vs Antigua GFC",
        "canales": []
    },
    {
        "hora": "22:00",
        "competición": "Copa Libertadores",
        "equipos": "Bahia vs Nacional",
        "canales": []
    },
    {
        "hora": "22:00",
        "competición": "Copa Libertadores",
        "equipos": "Deportivo Táchira vs LDU Quito",
        "canales": []
    },
    {
        "hora": "22:00",
        "competición": "Copa Sudamericana",
        "equipos": "Academia Puerto Cabello vs Vasco da Gama",
        "canales": []
    },
    {
        "hora": "22:00",
        "competición": "Copa Sudamericana",
        "equipos": "Unión Santa Fe vs Palestino",
        "canales": []
    },
    {
        "hora": "22:00",
        "competición": "Copa Sudamericana",
        "equipos": "Cerro Largo vs Universidad Católica",
        "canales": []
    },
    {
        "hora": "00:00",
        "competición": "Copa Libertadores",
        "equipos": "Universidad Chile vs Estudiantes",
        "canales": []
    },
    {
        "hora": "00:30",
        "competición": "Copa Sudamericana",
        "equipos": "Atlético Grau vs Grêmio",
        "canales": []
    },
    {
        "hora": "00:30",
        "competición": "Copa Sudamericana",
        "equipos": "Mushuc Runa vs Cruzeiro",
        "canales": []
    },
    {
        "hora": "00:30",
        "competición": "Copa Libertadores",
        "equipos": "Central Córdoba SdE vs Flamengo",
        "canales": []
    },
    {
        "hora": "00:30",
        "competición": "Copa Libertadores",
        "equipos": "Cerro Porteño vs Palmeiras",
        "canales": []
    },
    {
        "hora": "01:00",
        "competición": "Liga MX",
        "equipos": "Monterrey vs Toluca",
        "canales": []
    },
    {
        "hora": "02:00",
        "competición": "Copa Sudamericana",
        "equipos": "Once Caldas vs Unión Española",
        "canales": []
    },
    {
        "hora": "02:00",
        "competición": "Copa Libertadores",
        "equipos": "Sporting Cristal vs Bolívar",
        "canales": []
    },
    {
        "hora": "02:00",
        "competición": "Primera División",
        "equipos": "Alajuelense vs Municipal Liberia",
        "canales": []
    },
    {
        "hora": "03:10",
        "competición": "Liga MX",
        "equipos": "Pachuca vs América",
        "canales": []
    }
]